doit_redis.py
doit_redis-0.1.dist-info/DESCRIPTION.rst
doit_redis-0.1.dist-info/METADATA
doit_redis-0.1.dist-info/RECORD
doit_redis-0.1.dist-info/WHEEL
doit_redis-0.1.dist-info/entry_points.txt
doit_redis-0.1.dist-info/metadata.json
doit_redis-0.1.dist-info/top_level.txt
