Metadata-Version: 2.0
Name: doit-redis
Version: 0.1
Summary: Redis backend for doit
Home-page: http://github.com/saimn/doit-redis
Author: Simon Conseil
Author-email: contact@saimon.org
License: MIT
Keywords: doit
Platform: any
Requires-Python: >=3.5
Requires-Dist: doit
Requires-Dist: redis
